<?xml version="1.0" encoding="UTF-8"?>
<con:soapui-project id="65e6056d-08d2-4024-9849-3549522f1694" activeEnvironment="Default" name="REST Project 2" resourceRoot="" soapui-version="5.5.0" xmlns:con="http://eviware.com/soapui/config">
  <con:settings/>
  <con:interface xsi:type="con:RestService" id="aae30ec9-0364-48d3-84d2-f77a5e8e3bdc" wadlVersion="http://wadl.dev.java.net/2009/02" name="http://localhost:8080" type="rest" xmlns:xsi="http://www.w3.org/2001/XMLSchema-instance">
    <con:settings/>
    <con:definitionCache/>
    <con:endpoints>
      <con:endpoint>http://localhost:8080</con:endpoint>
    </con:endpoints>
    <con:resource name="" path="/DeleteCustomer" id="7dfff787-d9a2-437e-9c80-b522621b0f13">
      <con:settings/>
      <con:parameters/>
      <con:method name="1" id="6330aa61-ee58-4c06-a74a-94871c482a69" method="DELETE">
        <con:settings/>
        <con:parameters/>
        <con:representation type="RESPONSE">
          <con:mediaType>text/html; charset=iso-8859-1</con:mediaType>
          <con:status>200</con:status>
          <con:params/>
          <con:element>html</con:element>
        </con:representation>
        <con:representation type="REQUEST">
          <con:mediaType>application/json</con:mediaType>
          <con:params/>
        </con:representation>
        <con:representation type="RESPONSE">
          <con:mediaType>application/json; charset=utf-8</con:mediaType>
          <con:status>200</con:status>
          <con:params/>
        </con:representation>
        <con:request name="Request 1" id="0785d3aa-1c81-4fc0-bf92-5fdb55c3b561" mediaType="application/json" postQueryString="false">
          <con:settings>
            <con:setting id="com.eviware.soapui.impl.wsdl.WsdlRequest@request-headers">&lt;xml-fragment/></con:setting>
          </con:settings>
          <con:endpoint>http://localhost:9001</con:endpoint>
          <con:request/>
          <con:originalUri>http://localhost/AddCustomer</con:originalUri>
          <con:credentials>
            <con:authType>No Authorization</con:authType>
          </con:credentials>
          <con:jmsConfig JMSDeliveryMode="PERSISTENT"/>
          <con:jmsPropertyConfig/>
          <con:parameters/>
        </con:request>
      </con:method>
    </con:resource>
  </con:interface>
  <con:interface xsi:type="con:RestService" id="1d93fea9-9763-4af9-823c-8169e2bc8b2b" wadlVersion="http://wadl.dev.java.net/2009/02" name="http://localhost:8080" type="rest" xmlns:xsi="http://www.w3.org/2001/XMLSchema-instance">
    <con:settings/>
    <con:definitionCache/>
    <con:endpoints>
      <con:endpoint>http://localhost:8080</con:endpoint>
    </con:endpoints>
    <con:resource name="" path="/UpdateCustomer" id="542f762e-516a-4f56-9037-d06c4a08c840">
      <con:settings/>
      <con:parameters/>
      <con:method name="1" id="d758be8b-ecba-4b61-bfca-0309ce23c2cb" method="PUT">
        <con:settings/>
        <con:parameters/>
        <con:representation type="RESPONSE">
          <con:mediaType>application/json; charset=utf-8</con:mediaType>
          <con:status>200</con:status>
          <con:params/>
        </con:representation>
        <con:representation type="REQUEST">
          <con:mediaType>application/json</con:mediaType>
          <con:params/>
        </con:representation>
        <con:request name="Request 1" id="09e537d5-0421-44cb-8fd9-965448e16aba" mediaType="application/json" postQueryString="false">
          <con:settings>
            <con:setting id="com.eviware.soapui.impl.wsdl.WsdlRequest@request-headers">&lt;xml-fragment/></con:setting>
          </con:settings>
          <con:endpoint>http://localhost:9000</con:endpoint>
          <con:request/>
          <con:originalUri>http://localhost/UpdateCustomer</con:originalUri>
          <con:credentials>
            <con:authType>No Authorization</con:authType>
          </con:credentials>
          <con:jmsConfig JMSDeliveryMode="PERSISTENT"/>
          <con:jmsPropertyConfig/>
          <con:parameters/>
        </con:request>
      </con:method>
    </con:resource>
  </con:interface>
  <con:interface xsi:type="con:RestService" id="25eba02e-356f-404f-a296-e0459af9f708" wadlVersion="http://wadl.dev.java.net/2009/02" name="http://localhost:8080" type="rest" xmlns:xsi="http://www.w3.org/2001/XMLSchema-instance">
    <con:settings/>
    <con:definitionCache/>
    <con:endpoints>
      <con:endpoint>http://localhost:8080</con:endpoint>
    </con:endpoints>
    <con:resource name="" path="/AddCustomer" id="d6538891-cd4c-48af-9720-7145517fcf13">
      <con:settings/>
      <con:parameters/>
      <con:method name="1" id="d04f80e6-8dc0-417a-acf1-596c0eed31d6" method="POST">
        <con:settings/>
        <con:parameters/>
        <con:representation type="REQUEST">
          <con:mediaType>application/json</con:mediaType>
          <con:params/>
        </con:representation>
        <con:representation type="RESPONSE">
          <con:mediaType>text/html; charset=iso-8859-1</con:mediaType>
          <con:status>200</con:status>
          <con:params/>
          <con:element>html</con:element>
        </con:representation>
        <con:representation type="RESPONSE">
          <con:mediaType>application/json; charset=utf-8</con:mediaType>
          <con:status>200</con:status>
          <con:params/>
          <con:element>Response</con:element>
        </con:representation>
        <con:request name="Request 1" id="5ae70be9-c26d-4d14-82da-7f223b9886a2" mediaType="application/json" postQueryString="false">
          <con:settings>
            <con:setting id="com.eviware.soapui.impl.wsdl.WsdlRequest@request-headers">&lt;xml-fragment/></con:setting>
          </con:settings>
          <con:endpoint>http://localhost:9678</con:endpoint>
          <con:request/>
          <con:originalUri>http://localhost/AddCustomer</con:originalUri>
          <con:credentials>
            <con:authType>No Authorization</con:authType>
          </con:credentials>
          <con:jmsConfig JMSDeliveryMode="PERSISTENT"/>
          <con:jmsPropertyConfig/>
          <con:parameters/>
        </con:request>
      </con:method>
    </con:resource>
  </con:interface>
  <con:properties/>
  <con:wssContainer/>
  <con:oAuth2ProfileContainer/>
  <con:oAuth1ProfileContainer/>
</con:soapui-project>
